fast_aug-0.1.0.dist-info/METADATA
fast_aug-0.1.0.dist-info/WHEEL
fast_aug/flow/__init__.pyi
fast_aug/flow/__init__.py
fast_aug/models/__init__.pyi
fast_aug/models/__init__.py
fast_aug/base/__init__.pyi
fast_aug/base/__init__.py
fast_aug/__init__.pyi
fast_aug/__init__.py
fast_aug/text/__init__.pyi
fast_aug/text/__init__.py
fast_aug/fast_aug.cpython-38-x86_64-linux-gnu.so
fast_aug-0.1.0.dist-info/RECORD
