Metadata-Version: 2.1
Name: fast-aug
Version: 0.1.0
Classifier: Programming Language :: Python :: 3
Classifier: Development Status :: 3 - Alpha
Classifier: Programming Language :: Rust
Requires-Dist: pytest >=6.0.0, <8.0.0 ; extra == 'test'
Requires-Dist: black ==23.12.1 ; extra == 'test'
Requires-Dist: mypy >=1.0.0 ; extra == 'test'
Requires-Dist: ruff ==0.1.7 ; extra == 'test'
Requires-Dist: isort >=5.0.0, <6.0.0 ; extra == 'test'
Requires-Dist: maturin >=1.0, <2.0 ; extra == 'test'
Requires-Dist: pytest-benchmark[histogram] >=4.0.0, <5.0.0 ; extra == 'test'
Requires-Dist: pytest >=6.0.0, <8.0.0 ; extra == 'compare'
Requires-Dist: pytest-benchmark[histogram] >=4.0.0, <5.0.0 ; extra == 'compare'
Requires-Dist: pandas >=2.0.0, <3.0.0 ; extra == 'compare'
Requires-Dist: Pyarrow >=15.0.0, <16.0.0 ; extra == 'compare'
Requires-Dist: seaborn >=0.10.0, <1.0.0 ; extra == 'compare'
Requires-Dist: psutil >=5.0.0, <6.0.0 ; extra == 'compare'
Requires-Dist: tqdm >=4.0.0, <5.0.0 ; extra == 'compare'
Requires-Dist: nlpaug ==1.1.11 ; extra == 'compare'
Requires-Dist: fasttextaug ==0.1.1 ; extra == 'compare'
Provides-Extra: test
Provides-Extra: compare
Summary: Fast nlp augmentation library with rust backend
Home-Page: https://github.com/k4black/fast-aug
Author: Konstantin Chernyshev <kdchernyshev@gmail.com>
Author-email: Konstantin Chernyshev <kdchernyshev@gmail.com>
License: MIT
Requires-Python: >=3.8
Project-URL: Homepage, https://github.com/k4black/fast-aug
